[
  {
    "season": "겨울",
    "quote": "겨울이 오면 봄이 멀지 않으리.",
    "book": "<서풍에 부치는 노래>",
    "author": "퍼시 비시 셸리",
    "video": "winter_01.mp4",
    "color": "#ffffff"
  },
  {
    "season": "겨울",
    "quote": "추위 속에서 피어나는 꽃이 가장 아름답다.",
    "book": "<연금술사>",
    "author": "파울로 코엘료",
    "video": "winter_01.mp4",
    "color": "#ffffff"
  },
  {
    "season": "겨울",
    "quote": "시련이 지나면 반드시 따뜻한 날이 온다.",
    "book": "<브리다>",
    "author": "파울로 코엘료",
    "video": "winter_01.mp4",
    "color": "#ffffff"
  },
  {
    "season": "겨울",
    "quote": "고독은 영혼의 학교다.",
    "book": "<말테의 수기>",
    "author": "라이너 마리아 릴케",
    "video": "winter_01.mp4",
    "color": "#ffffff"
  },
  {
    "season": "겨울",
    "quote": "당신의 상처가 곧 당신의 힘이 된다.",
    "book": "<젊은 시인에게 보내는 편지>",
    "author": "라이너 마리아 릴케",
    "video": "winter_01.mp4",
    "color": "#ffffff"
  },
  {
    "season": "겨울",
    "quote": "어려운 것을 사랑하는 법을 배워라.",
    "book": "<젊은 시인에게 보내는 편지>",
    "author": "라이너 마리아 릴케",
    "video": "winter_01.mp4",
    "color": "#ffffff"
  },
  {
    "season": "겨울",
    "quote": "눈이 내리면 세상은 잠시 조용해진다.\n그때 비로소 들린다.",
    "book": "<설국>",
    "author": "가와바타 야스나리",
    "video": "winter_01.mp4",
    "color": "#ffffff"
  },
  {
    "season": "겨울",
    "quote": "국경의 긴 터널을 빠져나오자 설국이었다.",
    "book": "<설국>",
    "author": "가와바타 야스나리",
    "video": "winter_01.mp4",
    "color": "#ffffff"
  },
  {
    "season": "겨울",
    "quote": "차가운 겨울일수록 사람의 온기가 그립다.",
    "book": "<안나 카레니나>",
    "author": "톨스토이",
    "video": "winter_01.mp4",
    "color": "#ffffff"
  },
  {
    "season": "겨울",
    "quote": "행복한 가정은 모두 비슷하고,\n불행한 가정은 제각각 불행하다.",
    "book": "<안나 카레니나>",
    "author": "톨스토이",
    "video": "winter_01.mp4",
    "color": "#ffffff"
  },
  {
    "season": "겨울",
    "quote": "겨울밤 한 권의 책은 벽난로보다 따뜻하다.",
    "book": "<레미제라블>",
    "author": "빅토르 위고",
    "video": "winter_01.mp4",
    "color": "#ffffff"
  },
  {
    "season": "겨울",
    "quote": "사랑하는 것만으로도 충분히 살았다 할 수 있다.",
    "book": "<레미제라블>",
    "author": "빅토르 위고",
    "video": "winter_01.mp4",
    "color": "#ffffff"
  },
  {
    "season": "겨울",
    "quote": "혼자라는 것은 외로운 게 아니라\n온전한 것이다.",
    "book": "<노르웨이의 숲>",
    "author": "무라카미 하루키",
    "video": "winter_01.mp4",
    "color": "#ffffff"
  },
  {
    "season": "겨울",
    "quote": "죽음은 삶의 반대가 아니라,\n삶의 일부다.",
    "book": "<노르웨이의 숲>",
    "author": "무라카미 하루키",
    "video": "winter_01.mp4",
    "color": "#ffffff"
  },
  {
    "season": "겨울",
    "quote": "겨울을 견딘 사람만이 봄의 의미를 안다.",
    "book": "<카라마조프가의 형제들>",
    "author": "도스토옙스키",
    "video": "winter_02.mp4",
    "color": "#ffffff"
  },
  {
    "season": "겨울",
    "quote": "사랑은 모든 것을 이긴다.",
    "book": "<카라마조프가의 형제들>",
    "author": "도스토옙스키",
    "video": "winter_02.mp4",
    "color": "#ffffff"
  },
  {
    "season": "겨울",
    "quote": "추운 밤일수록 별은 더 선명하다.",
    "book": "<어린 왕자>",
    "author": "생텍쥐페리",
    "video": "winter_02.mp4",
    "color": "#ffffff"
  },
  {
    "season": "겨울",
    "quote": "눈물은 얼어도, 사랑은 얼지 않는다.",
    "book": "<어린 왕자>",
    "author": "생텍쥐페리",
    "video": "winter_02.mp4",
    "color": "#ffffff"
  },
  {
    "season": "겨울",
    "quote": "새해 첫날의 다짐은 작을수록 오래간다.",
    "book": "<철학의 위안>",
    "author": "알랭 드 보통",
    "video": "winter_02.mp4",
    "color": "#ffffff"
  },
  {
    "season": "겨울",
    "quote": "지금 이 순간을 사랑하라.\n그것이 전부다.",
    "book": "<철학의 위안>",
    "author": "알랭 드 보통",
    "video": "winter_02.mp4",
    "color": "#ffffff"
  },
  {
    "season": "겨울",
    "quote": "겨울은 독서의 계절이 아니라\n내면의 계절이다.",
    "book": "<월든>",
    "author": "헨리 데이비드 소로",
    "video": "winter_02.mp4",
    "color": "#ffffff"
  },
  {
    "season": "겨울",
    "quote": "고요함 속에서 진실이 말을 건다.",
    "book": "<월든>",
    "author": "헨리 데이비드 소로",
    "video": "winter_02.mp4",
    "color": "#ffffff"
  },
  {
    "season": "겨울",
    "quote": "한 해가 끝날 때,\n기억할 것은 결국 사람이다.",
    "book": "<엄마의 말뚝>",
    "author": "박완서",
    "video": "winter_02.mp4",
    "color": "#ffffff"
  },
  {
    "season": "겨울",
    "quote": "살아있는 한,\n내일은 새로운 이야기다.",
    "book": "<엄마의 말뚝>",
    "author": "박완서",
    "video": "winter_02.mp4",
    "color": "#ffffff"
  },
  {
    "season": "겨울",
    "quote": "눈 덮인 세상은 잠시 멈추라고 말한다.",
    "book": "<퀴즈쇼>",
    "author": "김영하",
    "video": "winter_02.mp4",
    "color": "#ffffff"
  },
  {
    "season": "겨울",
    "quote": "멈추는 것이 때로는 가장 빠른 길이다.",
    "book": "<알쓸신잡>",
    "author": "김영하",
    "video": "winter_02.mp4",
    "color": "#ffffff"
  },
  {
    "season": "겨울",
    "quote": "겨울을 나는 법을 아는 사람은 여름도 즐긴다.",
    "book": "<하악하악>",
    "author": "이외수",
    "video": "winter_02.mp4",
    "color": "#ffffff"
  },
  {
    "season": "겨울",
    "quote": "차가운 이성보다 따뜻한 직관이 옳을 때가 많다.",
    "book": "<감성사전>",
    "author": "이외수",
    "video": "winter_02.mp4",
    "color": "#ffffff"
  },
  {
    "season": "겨울",
    "quote": "새해는 새 페이지다.\n당신이 쓰면 된다.",
    "book": "<새벽 세 시의 몸부림>",
    "author": "류시화",
    "video": "winter_02.mp4",
    "color": "#ffffff"
  },
  {
    "season": "겨울",
    "quote": "눈이 녹으면 봄이 온다.\n기다리는 사람에게만.",
    "book": "<내가 사랑하는 사람>",
    "author": "정호승",
    "video": "winter_02.mp4",
    "color": "#ffffff"
  }
]